predatools/__init__.py
predatools/pandas_utils.py
predatools/read_data.py
predatools-0.1.1.dist-info/WHEEL
predatools-0.1.1.dist-info/METADATA
predatools-0.1.1.dist-info/RECORD
