Metadata-Version: 2.1
Name: predatools
Version: 0.1.1
Summary: 
Author: Kawin Liaowongphuthorn
Author-email: liaokangtai@gmail.com
Requires-Python: >=3.7,<4.0
Classifier: Programming Language :: Python :: 3
Classifier: Programming Language :: Python :: 3.7
Classifier: Programming Language :: Python :: 3.8
Requires-Dist: boto3 (>=1.11.9,<2.0.0)
Requires-Dist: fastavro (>=0.22.9,<0.23.0)
Requires-Dist: pandas (>=1.0.0,<2.0.0)
Requires-Dist: pyarrow (>=0.15.1,<0.16.0)
Requires-Dist: s3fs (>=0.4.0,<0.5.0)
Requires-Dist: tqdm (>=4.42.0,<5.0.0)
